tap_s3_csv/__init__.py
tap_s3_csv/config.py
tap_s3_csv/discover.py
tap_s3_csv/s3.py
tap_s3_csv/sync.py
pipelinewise_tap_s3_csv-3.0.1.dist-info/LICENSE
pipelinewise_tap_s3_csv-3.0.1.dist-info/METADATA
pipelinewise_tap_s3_csv-3.0.1.dist-info/WHEEL
pipelinewise_tap_s3_csv-3.0.1.dist-info/entry_points.txt
pipelinewise_tap_s3_csv-3.0.1.dist-info/top_level.txt
pipelinewise_tap_s3_csv-3.0.1.dist-info/RECORD
