Metadata-Version: 2.1
Name: pipelinewise-tap-s3-csv
Version: 3.0.1
Summary: Singer.io tap for extracting CSV files from S3 - PipelineWise compatible
Home-page: https://github.com/transferwise/pipelinewise-tap-s3-csv
Author: TransferWise
Classifier: License :: OSI Approved :: GNU Affero General Public License v3
Classifier: Programming Language :: Python :: 3 :: Only
Provides-Extra: dev
Provides-Extra: test
License-File: LICENSE
